phlashlib/__init__.py
phlashlib/gpu.py
phlashlib/hmm.py
phlashlib/iicr.py
phlashlib/kernel.cu
phlashlib/loglik.py
phlashlib/params.py
phlashlib/transition.py
phlashlib-0.1.1.dist-info/WHEEL
phlashlib-0.1.1.dist-info/METADATA
phlashlib-0.1.1.dist-info/RECORD
