Metadata-Version: 2.3
Name: phlashlib
Version: 0.1.1
Summary: Fast evaluation of SMC' likelihood for population genetic data
Author: Jonathan Terhorst
Author-email: Jonathan Terhorst <jonth@umich.edu>
Requires-Dist: beartype>=0.21.0
Requires-Dist: dask>=2024.8.0
Requires-Dist: equinox>=0.13.0
Requires-Dist: jax>=0.7.2
Requires-Dist: jaxtyping>=0.3.2
Requires-Dist: loguru>=0.7.3
Requires-Dist: optimistix>=0.0.10
Requires-Dist: sgkit>=0.10.0
Requires-Dist: sparse>=0.17.0
Requires-Dist: pytest>=8.4.1 ; extra == 'dev'
Requires-Dist: jax[cuda12]>=0.7.2 ; extra == 'gpu'
Requires-Dist: cuda-bindings>=12.3,<13.0 ; extra == 'gpu'
Requires-Dist: cuda-core>=0.3.1 ; extra == 'gpu'
Requires-Dist: cuda-python>=12.2,<13 ; extra == 'gpu'
Requires-Dist: cupy-cuda12x>=13.5.1 ; extra == 'gpu'
Requires-Python: >=3.12
Provides-Extra: dev
Provides-Extra: gpu
